haystack_test_package/__init__.py
haystack_test_package/app.py
haystack_test_package/cache.py
haystack_test_package/dynamo.py
haystack_test_package/model_store.py
haystack_test_package/settings.py
haystack_test_package-0.1.3.dist-info/METADATA
haystack_test_package-0.1.3.dist-info/WHEEL
haystack_test_package-0.1.3.dist-info/top_level.txt
haystack_test_package-0.1.3.dist-info/RECORD
