Metadata-Version: 2.4
Name: haystack-test-package
Version: 0.1.3
Summary: Functions related to Haystack ML
Author-email: Oscar Vega <oscar@haystack.tv>
License: MIT
Requires-Python: >=3.11
Requires-Dist: pydantic==2.5.0
Requires-Dist: cachetools==5.5.2
Requires-Dist: cloudpickle==2.2.1
Requires-Dist: aioboto3==12.0.0
Requires-Dist: fastapi==0.104.1
Requires-Dist: pydantic-settings==2.2
